LICENSE
MANIFEST.in
README.md
requirements.txt
setup.py
tests/test_environ.py
tests/test_imports.py
tests/test_introspect.py
tests/test_utils.py
volkanic/__init__.py
volkanic/__main__.py
volkanic/cmdline.py
volkanic/compat.py
volkanic/environ.py
volkanic/errors.py
volkanic/introspect.py
volkanic/utils.py
volkanic.egg-info/PKG-INFO
volkanic.egg-info/SOURCES.txt
volkanic.egg-info/dependency_links.txt
volkanic.egg-info/entry_points.txt
volkanic.egg-info/not-zip-safe
volkanic.egg-info/requires.txt
volkanic.egg-info/top_level.txt