Metadata-Version: 2.1
Name: volkanic
Version: 0.4.3
Summary: access config and CLI easily and elegantly
Home-page: https://github.com/frozflame/volkanic
Author: frozflame
Author-email: frozflame@outlook.com
License: GNU General Public License (GPL)
Classifier: Programming Language :: Python
Classifier: Programming Language :: Python :: 3
Classifier: Programming Language :: Python :: 3.5
Classifier: Programming Language :: Python :: 3.6
Classifier: Programming Language :: Python :: 3.7
Classifier: Programming Language :: Python :: 3.8
Classifier: Programming Language :: Python :: 3.9
Classifier: Programming Language :: Python :: 3.10
Requires-Python: >=3.5
License-File: LICENSE
